XStatic_jQuery-3.5.1.1-py3.13-nspkg.pth
xstatic/pkg/jquery/__init__.py
xstatic/pkg/jquery/data/jquery.js
xstatic/pkg/jquery/data/jquery.min.js
xstatic/pkg/jquery/data/jquery.min.map
xstatic/pkg/jquery/data/jquery.slim.js
xstatic/pkg/jquery/data/jquery.slim.min.js
xstatic/pkg/jquery/data/jquery.slim.min.map
xstatic_jquery-3.5.1.1.dist-info/METADATA
xstatic_jquery-3.5.1.1.dist-info/WHEEL
xstatic_jquery-3.5.1.1.dist-info/namespace_packages.txt
xstatic_jquery-3.5.1.1.dist-info/top_level.txt
xstatic_jquery-3.5.1.1.dist-info/RECORD
