Metadata-Version: 2.4
Name: XStatic-jQuery
Version: 3.5.1.1
Summary: jQuery 3.5.1 (XStatic packaging standard)
Home-page: https://jquery.com/
Maintainer: Thomas Waldmann
Maintainer-email: tw@waldmann-edv.de
License: (same as jQuery)
Keywords: jquery xstatic
Platform: any
Dynamic: description
Dynamic: home-page
Dynamic: keywords
Dynamic: license
Dynamic: maintainer
Dynamic: maintainer-email
Dynamic: platform
Dynamic: summary
